umi/__init__.py
umi/lumi/README.md
umi/lumi/__init__.py
umi/lumi/rtl/lumi.v
umi/lumi/rtl/lumi_crossbar.v
umi/lumi/rtl/lumi_regmap.vh
umi/lumi/rtl/lumi_regs.v
umi/lumi/rtl/lumi_rx.v
umi/lumi/rtl/lumi_tx.v
umi/lumi/testbench/config.vlt
umi/lumi/testbench/test_lumi.py
umi/lumi/testbench/test_lumi_rnd.py
umi/lumi/testbench/testbench_lumi.sv
umi/umi/__init__.py
umi/umi/rtl/umi_arbiter.v
umi/umi/rtl/umi_crossbar.v
umi/umi/rtl/umi_decode.v
umi/umi/rtl/umi_endpoint.v
umi/umi/rtl/umi_fifo.v
umi/umi/rtl/umi_fifo_flex.v
umi/umi/rtl/umi_isolate.v
umi/umi/rtl/umi_mem_agent.v
umi/umi/rtl/umi_messages.vh
umi/umi/rtl/umi_mux.v
umi/umi/rtl/umi_pack.v
umi/umi/rtl/umi_pipeline.v
umi/umi/rtl/umi_priority.v
umi/umi/rtl/umi_ram.v
umi/umi/rtl/umi_regif.v
umi/umi/rtl/umi_splitter.v
umi/umi/rtl/umi_stimulus.v
umi/umi/rtl/umi_unpack.v
umi/umi/testbench/config.vlt
umi/umi/testbench/dut_umi_fifo.v
umi/umi/testbench/dut_umi_fifo_flex.v
umi/umi/testbench/test_crossbar.py
umi/umi/testbench/test_fifo.py
umi/umi/testbench/test_fifo_flex.py
umi/umi/testbench/test_mem_agent.py
umi/umi/testbench/test_regif.py
umi/umi/testbench/test_umi_ram.py
umi/umi/testbench/testbench_crossbar.sv
umi/umi/testbench/testbench_fifo.sv
umi/umi/testbench/testbench_fifo_flex.sv
umi/umi/testbench/testbench_mem_agent.sv
umi/umi/testbench/testbench_regif.sv
umi/umi/testbench/testbench_umi_ram.sv
umi/umi/testbench/umi_testbench.py
umi/umi/testbench/cpp/umi_testbench.cc
umi/utils/rtl/README.md
umi/utils/rtl/axilite2umi.v
umi/utils/rtl/tl-uh.vh
umi/utils/rtl/tl2umi_np.v
umi/utils/rtl/umi2apb.v
umi/utils/rtl/umi2axilite.v
umi/utils/rtl/umi2tl_np.v
umi/utils/rtl/umi_address_remap.v
umi/utils/rtl/umi_data_aggregator.v
umi/utils/rtl/umi_packet_merge_greedy.v
umi/utils/testbench/buffer.memh
umi/utils/testbench/buffer_axilite.memh
umi/utils/testbench/config.h
umi/utils/testbench/config.vlt
umi/utils/testbench/tb_axilite2umi.v
umi/utils/testbench/tb_tl2umi_np.v
umi/utils/testbench/tb_umi_data_aggregator.v
umi_hw-0.1.2.dist-info/AUTHORS
umi_hw-0.1.2.dist-info/LICENSE
umi_hw-0.1.2.dist-info/METADATA
umi_hw-0.1.2.dist-info/WHEEL
umi_hw-0.1.2.dist-info/top_level.txt
umi_hw-0.1.2.dist-info/RECORD
