Metadata-Version: 2.1
Name: umi-hw
Version: 0.1.2
Summary: Universal Memory Interface (UMI)
Author: Zero ASIC
License: Apache License
Project-URL: Homepage, https://github.com/zeroasiccorp/umi
Requires-Python: >=3.8
License-File: LICENSE
License-File: AUTHORS
Requires-Dist: siliconcompiler >=0.26.0
Requires-Dist: lambdalib <0.2.10,>=0.2.9
Provides-Extra: test
Requires-Dist: switchboard-hw >=0.2.14 ; extra == 'test'
Requires-Dist: flake8 ==7.1.0 ; extra == 'test'
